subtitler_util/__init__.py
subtitler_util/lang.tsv
subtitler_util/subtitler.py
subtitler_util-1.0.3.dist-info/LICENSE
subtitler_util-1.0.3.dist-info/METADATA
subtitler_util-1.0.3.dist-info/WHEEL
subtitler_util-1.0.3.dist-info/entry_points.txt
subtitler_util-1.0.3.dist-info/top_level.txt
subtitler_util-1.0.3.dist-info/RECORD
