Metadata-Version: 2.1
Name: subtitler_util
Version: 1.0.3
Summary: A utility that uses Whisper to transcribe videos and various translation APIs to translate the transcribed text and save them as SRT (subtitle) files
Author-email: Anupam <anupam@anupamkumar.me>
Project-URL: Homepage, https://anupamkumar.me
Project-URL: GitHub, https://github.com/anupamkumar/subtitler
Project-URL: Issues, https://github.com/anupamkumar/subtitler/issues
Classifier: Development Status :: 5 - Production/Stable
Classifier: Environment :: Console
Classifier: Environment :: GPU
Classifier: Environment :: GPU :: NVIDIA CUDA
Classifier: Environment :: MacOS X
Classifier: Environment :: Win32 (MS Windows)
Classifier: Environment :: X11 Applications :: GTK
Classifier: Intended Audience :: Other Audience
Classifier: Intended Audience :: Information Technology
Classifier: Intended Audience :: System Administrators
Classifier: Intended Audience :: End Users/Desktop
Classifier: License :: Freely Distributable
Classifier: Natural Language :: English
Classifier: Programming Language :: Python :: 3 :: Only
Classifier: Operating System :: OS Independent
Classifier: Topic :: Multimedia :: Video
Classifier: Topic :: Multimedia
Classifier: Topic :: Utilities
Requires-Python: >=3.10
License-File: LICENSE
Requires-Dist: ffmpeg-python
Requires-Dist: openai-whisper
Requires-Dist: Gooey
Requires-Dist: deep-translator
